README.rst
setup.py
xrsdkit/__init__.py
xrsdkit/definitions.py
xrsdkit.egg-info/PKG-INFO
xrsdkit.egg-info/SOURCES.txt
xrsdkit.egg-info/dependency_links.txt
xrsdkit.egg-info/entry_points.txt
xrsdkit.egg-info/requires.txt
xrsdkit.egg-info/top_level.txt
xrsdkit/db/__init__.py
xrsdkit/models/__init__.py
xrsdkit/models/classifier.py
xrsdkit/models/predict.py
xrsdkit/models/regressor.py
xrsdkit/models/train.py
xrsdkit/models/xrsd_model.py
xrsdkit/scattering/__init__.py
xrsdkit/scattering/atomic_scattering_params.yml
xrsdkit/scattering/form_factors.py
xrsdkit/scattering/structure_factors.py
xrsdkit/scattering/symmetries.py
xrsdkit/system/__init__.py
xrsdkit/system/noise.py
xrsdkit/system/population.py
xrsdkit/tools/__init__.py
xrsdkit/tools/devtools.py
xrsdkit/tools/peak_math.py
xrsdkit/tools/profiler.py
xrsdkit/tools/visualization_tools.py
xrsdkit/tools/ymltools.py
xrsdkit/visualization/__init__.py
xrsdkit/visualization/gui.py