Metadata-Version: 1.0
Name: xrsdkit
Version: 0.2.4
Summary: Scattering and diffraction modeling and analysis toolkit
Home-page: https://github.com/scattering-central/xrsdkit.git
Author: SSRL
Author-email: paws-developers@slac.stanford.edu
License: BSD
Platform: UNKNOWN
